Flask_Resize-2.0.4.dist-info/DESCRIPTION.rst
Flask_Resize-2.0.4.dist-info/METADATA
Flask_Resize-2.0.4.dist-info/RECORD
Flask_Resize-2.0.4.dist-info/WHEEL
Flask_Resize-2.0.4.dist-info/entry_points.txt
Flask_Resize-2.0.4.dist-info/metadata.json
Flask_Resize-2.0.4.dist-info/pbr.json
Flask_Resize-2.0.4.dist-info/top_level.txt
flask_resize/__init__.py
flask_resize/_compat.py
flask_resize/bin.py
flask_resize/cache.py
flask_resize/configuration.py
flask_resize/constants.py
flask_resize/exc.py
flask_resize/metadata.py
flask_resize/resizing.py
flask_resize/storage.py
flask_resize/utils.py
flask_resize/fonts/DroidSans.ttf
tests/__init__.py
tests/_mocking.py
tests/base.py
tests/decorators.py
tests/test_bin.py
tests/test_cache.py
tests/test_concurrency.py
tests/test_conf.py
tests/test_resize.py
tests/test_storage.py
tests/test_utils.py
